spreadmagic/__init__.py
spreadmagic/spreadmagic.py
spreadmagic-2.6.1.dist-info/METADATA
spreadmagic-2.6.1.dist-info/WHEEL
spreadmagic-2.6.1.dist-info/top_level.txt
spreadmagic-2.6.1.dist-info/RECORD
