Metadata-Version: 2.2
Name: spreadmagic
Version: 2.6.1
Summary: This Python package is a magic command that executes Python code in code cells on Jupyter and Google Colab using PyScript within an iframe.
Author: Uniras
Author-email: tkappeng@gmail.com
License: MIT License
Project-URL: Homepage, https://github.com/uniras/SpreadMagic
Project-URL: Repository, https://github.com/uniras/SpreadMagic
Keywords: PyScript,jupyter,magic,colab,iframe,jspreadsheet
Classifier: Development Status :: 5 - Production/Stable
Classifier: Intended Audience :: Developers
Classifier: License :: OSI Approved :: MIT License
Classifier: Programming Language :: Python :: 3
Classifier: Programming Language :: Python :: 3.7
Classifier: Programming Language :: Python :: 3.8
Classifier: Programming Language :: Python :: 3.9
Classifier: Programming Language :: Python :: 3.10
Classifier: Programming Language :: Python :: 3 :: Only
Classifier: Topic :: Software Development :: Libraries
Classifier: Topic :: Software Development :: Libraries :: Python Modules
Classifier: Topic :: Utilities
